test_cmd_x.py
test_cmd_x-2.0.3.dist-info/LICENSE
test_cmd_x-2.0.3.dist-info/METADATA
test_cmd_x-2.0.3.dist-info/WHEEL
test_cmd_x-2.0.3.dist-info/entry_points.txt
test_cmd_x-2.0.3.dist-info/top_level.txt
test_cmd_x-2.0.3.dist-info/RECORD
