Metadata-Version: 2.1
Name: test-cmd-x
Version: 2.0.3
Summary: Tool for black-box testing command-line programs, with extensions
Home-page: https://github.com/agerasev/test_cmd_x
Author: Alexey Gerasev
Author-email: nthend.iipa@gmail.com
License: Apache
Download-URL: https://github.com/agerasev/test_cmd_x/tarball/2.0.3
Keywords: command line terminal functional black box testing arguments stdin stdout stderr
Platform: UNKNOWN
Classifier: Topic :: Software Development :: Quality Assurance
Classifier: Topic :: Software Development :: Testing
Classifier: License :: OSI Approved :: Apache Software License
Classifier: Environment :: Console
